wonder_sdk/__init__.py
wonder_sdk/app.py
wonder_sdk/config.py
wonder_sdk/firestore.py
wonder_sdk/health.py
wonder_sdk/logger.py
wonder_sdk/pubsub.py
wonder_sdk/shutdown.py
wonder_sdk/storage.py
wonder_sdk/threading.py
wonder_sdk/translation.py
wonder_sdk-0.2.5.dist-info/LICENCE
wonder_sdk-0.2.5.dist-info/METADATA
wonder_sdk-0.2.5.dist-info/WHEEL
wonder_sdk-0.2.5.dist-info/top_level.txt
wonder_sdk-0.2.5.dist-info/RECORD
