Metadata-Version: 2.1
Name: wonder-sdk
Version: 0.2.5
Summary: Python SDK for common Wonder functions
Author: basri
Author-email: basri@codeway.co
License-File: LICENCE
